{
    "port": "COM3",
    "baudrate": 115200,
    "Room A": [
              {
            "id": "A01",
            "X": -120.000,
            "Y": -240.000
        },
        {
            "id": "A02",
            "X": -142.000,
            "Y": -1510.000
        },
        {
            "id": "A03",
            "X": -142.000,
            "Y": -1160.000
        },
        {
            "id": "A04",
            "X": -142.000,
            "Y": -830.000
        },
        {
            "id": "A05",
            "X": -142.000,
            "Y": -490.000
        },
        {
            "id": "A06",
            "X": -142.000,
            "Y": -140.000
        },
        {
            "id": "A07",
            "X": -812.000,
            "Y": -1890.000
        },
        {
            "id": "A08",
            "X": -812.000,
            "Y": -1540.000
        },
        {
            "id": "A09",
            "X": -812.000,
            "Y": -1180.000
        },
        {
            "id": "A10",
            "X": -812.000,
            "Y": -840.000
        },
        {
            "id": "A11",
            "X": -812.000,
            "Y": -490.000
        },
        {
            "id": "A12",
            "X": -812.000,
            "Y": -150.000
        }
    ],
    "Room B": [
              {
            "id": "B01",
            "X": -142.000,
            "Y": -1840.000
        },
        {
            "id": "B02",
            "X": -142.000,
            "Y": -1510.000
        },
        {
            "id": "B03",
            "X": -142.000,
            "Y": -1160.000
        },
        {
            "id": "B04",
            "X": -142.000,
            "Y": -830.000
        },
        {
            "id": "B05",
            "X": -142.000,
            "Y": -490.000
        },
        {
            "id": "B06",
            "X": -142.000,
            "Y": -140.000
        },
        {
            "id": "B07",
            "X": -812.000,
            "Y": -1890.000
        },
        {
            "id": "B08",
            "X": -812.000,
            "Y": -1540.000
        },
        {
            "id": "B09",
            "X": -812.000,
            "Y": -1180.000
        },
        {
            "id": "B10",
            "X": -812.000,
            "Y": -840.000
        },
        {
            "id": "B11",
            "X": -812.000,
            "Y": -490.000
        },
        {
            "id": "B12",
            "X": -812.000,
            "Y": -150.000
        }
    ],
    "dense_grid": [
        {"X": 0.0, "Y": 0.0},
        {"X": 10.0, "Y": 0.0},
        {"X": 20.0, "Y": 0.0},
        {"X": 0.0, "Y": 10.0},
        {"X": 10.0, "Y": 10.0},
        {"X": 20.0, "Y": 10.0},
        {"X": 0.0, "Y": 20.0},
        {"X": 10.0, "Y": 20.0},
        {"X": 20.0, "Y": 20.0}
    ],
    "python_dependencies": [
        {"name": "pillow", "import": "PIL"},
        {"name": "opencv-python", "import": "cv2"},
        {"name": "pyserial", "import": "serial"},
        {"name": "numpy", "import": "numpy"},
        {"name": "piexif", "import": "piexif"},
        {"name": "pandas", "import": "pandas"},
        {"name": "matplotlib", "import": "matplotlib"}
    ]
}