[
    {
        "id": 1,
        "X": 0.0,
        "Y": 0.0
    },
    {
        "id": 2,
        "X": 0.0,
        "Y": -100.0
    },
    {
        "id": 3,
        "X": 0.0,
        "Y": -200.0
    },
    {
        "id": 4,
        "X": 0.0,
        "Y": -300.0
    },
    {
        "id": 5,
        "X": 0.0,
        "Y": -400.0
    },
    {
        "id": 6,
        "X": 0.0,
        "Y": -500.0
    },
    {
        "id": 7,
        "X": 0.0,
        "Y": -600.0
    },
    {
        "id": 8,
        "X": 0.0,
        "Y": -700.0
    },
    {
        "id": 9,
        "X": 0.0,
        "Y": -800.0
    },
    {
        "id": 10,
        "X": 0.0,
        "Y": -900.0
    },
    {
        "id": 11,
        "X": 0.0,
        "Y": -1000.0
    },
    {
        "id": 12,
        "X": 0.0,
        "Y": -1100.0
    },
    {
        "id": 13,
        "X": 0.0,
        "Y": -1200.0
    },
    {
        "id": 14,
        "X": 0.0,
        "Y": -1300.0
    },
    {
        "id": 15,
        "X": 0.0,
        "Y": -1400.0
    },
    {
        "id": 16,
        "X": 0.0,
        "Y": -1500.0
    },
    {
        "id": 17,
        "X": 0.0,
        "Y": -1600.0
    },
    {
        "id": 18,
        "X": 0.0,
        "Y": -1700.0
    },
    {
        "id": 19,
        "X": 0.0,
        "Y": -1800.0
    },
    {
        "id": 20,
        "X": 0.0,
        "Y": -1900.0
    },
    {
        "id": 21,
        "X": 0.0,
        "Y": -2000.0
    },
    {
        "id": 22,
        "X": -100.0,
        "Y": -2000.0
    },
    {
        "id": 23,
        "X": -100.0,
        "Y": -1900.0
    },
    {
        "id": 24,
        "X": -100.0,
        "Y": -1800.0
    },
    {
        "id": 25,
        "X": -100.0,
        "Y": -1700.0
    },
    {
        "id": 26,
        "X": -100.0,
        "Y": -1600.0
    },
    {
        "id": 27,
        "X": -100.0,
        "Y": -1500.0
    },
    {
        "id": 28,
        "X": -100.0,
        "Y": -1400.0
    },
    {
        "id": 29,
        "X": -100.0,
        "Y": -1300.0
    },
    {
        "id": 30,
        "X": -100.0,
        "Y": -1200.0
    },
    {
        "id": 31,
        "X": -100.0,
        "Y": -1100.0
    },
    {
        "id": 32,
        "X": -100.0,
        "Y": -1000.0
    },
    {
        "id": 33,
        "X": -100.0,
        "Y": -900.0
    },
    {
        "id": 34,
        "X": -100.0,
        "Y": -800.0
    },
    {
        "id": 35,
        "X": -100.0,
        "Y": -700.0
    },
    {
        "id": 36,
        "X": -100.0,
        "Y": -600.0
    },
    {
        "id": 37,
        "X": -100.0,
        "Y": -500.0
    },
    {
        "id": 38,
        "X": -100.0,
        "Y": -400.0
    },
    {
        "id": 39,
        "X": -100.0,
        "Y": -300.0
    },
    {
        "id": 40,
        "X": -100.0,
        "Y": -200.0
    },
    {
        "id": 41,
        "X": -100.0,
        "Y": -100.0
    },
    {
        "id": 42,
        "X": -100.0,
        "Y": 0.0
    },
    {
        "id": 43,
        "X": -200.0,
        "Y": 0.0
    },
    {
        "id": 44,
        "X": -200.0,
        "Y": -100.0
    },
    {
        "id": 45,
        "X": -200.0,
        "Y": -200.0
    },
    {
        "id": 46,
        "X": -200.0,
        "Y": -300.0
    },
    {
        "id": 47,
        "X": -200.0,
        "Y": -400.0
    },
    {
        "id": 48,
        "X": -200.0,
        "Y": -500.0
    },
    {
        "id": 49,
        "X": -200.0,
        "Y": -600.0
    },
    {
        "id": 50,
        "X": -200.0,
        "Y": -700.0
    },
    {
        "id": 51,
        "X": -200.0,
        "Y": -800.0
    },
    {
        "id": 52,
        "X": -200.0,
        "Y": -900.0
    },
    {
        "id": 53,
        "X": -200.0,
        "Y": -1000.0
    },
    {
        "id": 54,
        "X": -200.0,
        "Y": -1100.0
    },
    {
        "id": 55,
        "X": -200.0,
        "Y": -1200.0
    },
    {
        "id": 56,
        "X": -200.0,
        "Y": -1300.0
    },
    {
        "id": 57,
        "X": -200.0,
        "Y": -1400.0
    },
    {
        "id": 58,
        "X": -200.0,
        "Y": -1500.0
    },
    {
        "id": 59,
        "X": -200.0,
        "Y": -1600.0
    },
    {
        "id": 60,
        "X": -200.0,
        "Y": -1700.0
    },
    {
        "id": 61,
        "X": -200.0,
        "Y": -1800.0
    },
    {
        "id": 62,
        "X": -200.0,
        "Y": -1900.0
    },
    {
        "id": 63,
        "X": -200.0,
        "Y": -2000.0
    },
    {
        "id": 64,
        "X": -300.0,
        "Y": -2000.0
    },
    {
        "id": 65,
        "X": -300.0,
        "Y": -1900.0
    },
    {
        "id": 66,
        "X": -300.0,
        "Y": -1800.0
    },
    {
        "id": 67,
        "X": -300.0,
        "Y": -1700.0
    },
    {
        "id": 68,
        "X": -300.0,
        "Y": -1600.0
    },
    {
        "id": 69,
        "X": -300.0,
        "Y": -1500.0
    },
    {
        "id": 70,
        "X": -300.0,
        "Y": -1400.0
    },
    {
        "id": 71,
        "X": -300.0,
        "Y": -1300.0
    },
    {
        "id": 72,
        "X": -300.0,
        "Y": -1200.0
    },
    {
        "id": 73,
        "X": -300.0,
        "Y": -1100.0
    },
    {
        "id": 74,
        "X": -300.0,
        "Y": -1000.0
    },
    {
        "id": 75,
        "X": -300.0,
        "Y": -900.0
    },
    {
        "id": 76,
        "X": -300.0,
        "Y": -800.0
    },
    {
        "id": 77,
        "X": -300.0,
        "Y": -700.0
    },
    {
        "id": 78,
        "X": -300.0,
        "Y": -600.0
    },
    {
        "id": 79,
        "X": -300.0,
        "Y": -500.0
    },
    {
        "id": 80,
        "X": -300.0,
        "Y": -400.0
    },
    {
        "id": 81,
        "X": -300.0,
        "Y": -300.0
    },
    {
        "id": 82,
        "X": -300.0,
        "Y": -200.0
    },
    {
        "id": 83,
        "X": -300.0,
        "Y": -100.0
    },
    {
        "id": 84,
        "X": -300.0,
        "Y": 0.0
    },
    {
        "id": 85,
        "X": -400.0,
        "Y": 0.0
    },
    {
        "id": 86,
        "X": -400.0,
        "Y": -100.0
    },
    {
        "id": 87,
        "X": -400.0,
        "Y": -200.0
    },
    {
        "id": 88,
        "X": -400.0,
        "Y": -300.0
    },
    {
        "id": 89,
        "X": -400.0,
        "Y": -400.0
    },
    {
        "id": 90,
        "X": -400.0,
        "Y": -500.0
    },
    {
        "id": 91,
        "X": -400.0,
        "Y": -600.0
    },
    {
        "id": 92,
        "X": -400.0,
        "Y": -700.0
    },
    {
        "id": 93,
        "X": -400.0,
        "Y": -800.0
    },
    {
        "id": 94,
        "X": -400.0,
        "Y": -900.0
    },
    {
        "id": 95,
        "X": -400.0,
        "Y": -1000.0
    },
    {
        "id": 96,
        "X": -400.0,
        "Y": -1100.0
    },
    {
        "id": 97,
        "X": -400.0,
        "Y": -1200.0
    },
    {
        "id": 98,
        "X": -400.0,
        "Y": -1300.0
    },
    {
        "id": 99,
        "X": -400.0,
        "Y": -1400.0
    },
    {
        "id": 100,
        "X": -400.0,
        "Y": -1500.0
    },
    {
        "id": 101,
        "X": -400.0,
        "Y": -1600.0
    },
    {
        "id": 102,
        "X": -400.0,
        "Y": -1700.0
    },
    {
        "id": 103,
        "X": -400.0,
        "Y": -1800.0
    },
    {
        "id": 104,
        "X": -400.0,
        "Y": -1900.0
    },
    {
        "id": 105,
        "X": -400.0,
        "Y": -2000.0
    },
    {
        "id": 106,
        "X": -500.0,
        "Y": -2000.0
    },
    {
        "id": 107,
        "X": -500.0,
        "Y": -1900.0
    },
    {
        "id": 108,
        "X": -500.0,
        "Y": -1800.0
    },
    {
        "id": 109,
        "X": -500.0,
        "Y": -1700.0
    },
    {
        "id": 110,
        "X": -500.0,
        "Y": -1600.0
    },
    {
        "id": 111,
        "X": -500.0,
        "Y": -1500.0
    },
    {
        "id": 112,
        "X": -500.0,
        "Y": -1400.0
    },
    {
        "id": 113,
        "X": -500.0,
        "Y": -1300.0
    },
    {
        "id": 114,
        "X": -500.0,
        "Y": -1200.0
    },
    {
        "id": 115,
        "X": -500.0,
        "Y": -1100.0
    },
    {
        "id": 116,
        "X": -500.0,
        "Y": -1000.0
    },
    {
        "id": 117,
        "X": -500.0,
        "Y": -900.0
    },
    {
        "id": 118,
        "X": -500.0,
        "Y": -800.0
    },
    {
        "id": 119,
        "X": -500.0,
        "Y": -700.0
    },
    {
        "id": 120,
        "X": -500.0,
        "Y": -600.0
    },
    {
        "id": 121,
        "X": -500.0,
        "Y": -500.0
    },
    {
        "id": 122,
        "X": -500.0,
        "Y": -400.0
    },
    {
        "id": 123,
        "X": -500.0,
        "Y": -300.0
    },
    {
        "id": 124,
        "X": -500.0,
        "Y": -200.0
    },
    {
        "id": 125,
        "X": -500.0,
        "Y": -100.0
    },
    {
        "id": 126,
        "X": -500.0,
        "Y": 0.0
    },
    {
        "id": 127,
        "X": -600.0,
        "Y": 0.0
    },
    {
        "id": 128,
        "X": -600.0,
        "Y": -100.0
    },
    {
        "id": 129,
        "X": -600.0,
        "Y": -200.0
    },
    {
        "id": 130,
        "X": -600.0,
        "Y": -300.0
    },
    {
        "id": 131,
        "X": -600.0,
        "Y": -400.0
    },
    {
        "id": 132,
        "X": -600.0,
        "Y": -500.0
    },
    {
        "id": 133,
        "X": -600.0,
        "Y": -600.0
    },
    {
        "id": 134,
        "X": -600.0,
        "Y": -700.0
    },
    {
        "id": 135,
        "X": -600.0,
        "Y": -800.0
    },
    {
        "id": 136,
        "X": -600.0,
        "Y": -900.0
    },
    {
        "id": 137,
        "X": -600.0,
        "Y": -1000.0
    },
    {
        "id": 138,
        "X": -600.0,
        "Y": -1100.0
    },
    {
        "id": 139,
        "X": -600.0,
        "Y": -1200.0
    },
    {
        "id": 140,
        "X": -600.0,
        "Y": -1300.0
    },
    {
        "id": 141,
        "X": -600.0,
        "Y": -1400.0
    },
    {
        "id": 142,
        "X": -600.0,
        "Y": -1500.0
    },
    {
        "id": 143,
        "X": -600.0,
        "Y": -1600.0
    },
    {
        "id": 144,
        "X": -600.0,
        "Y": -1700.0
    },
    {
        "id": 145,
        "X": -600.0,
        "Y": -1800.0
    },
    {
        "id": 146,
        "X": -600.0,
        "Y": -1900.0
    },
    {
        "id": 147,
        "X": -600.0,
        "Y": -2000.0
    },
    {
        "id": 148,
        "X": -700.0,
        "Y": -2000.0
    },
    {
        "id": 149,
        "X": -700.0,
        "Y": -1900.0
    },
    {
        "id": 150,
        "X": -700.0,
        "Y": -1800.0
    },
    {
        "id": 151,
        "X": -700.0,
        "Y": -1700.0
    },
    {
        "id": 152,
        "X": -700.0,
        "Y": -1600.0
    },
    {
        "id": 153,
        "X": -700.0,
        "Y": -1500.0
    },
    {
        "id": 154,
        "X": -700.0,
        "Y": -1400.0
    },
    {
        "id": 155,
        "X": -700.0,
        "Y": -1300.0
    },
    {
        "id": 156,
        "X": -700.0,
        "Y": -1200.0
    },
    {
        "id": 157,
        "X": -700.0,
        "Y": -1100.0
    },
    {
        "id": 158,
        "X": -700.0,
        "Y": -1000.0
    },
    {
        "id": 159,
        "X": -700.0,
        "Y": -900.0
    },
    {
        "id": 160,
        "X": -700.0,
        "Y": -800.0
    },
    {
        "id": 161,
        "X": -700.0,
        "Y": -700.0
    },
    {
        "id": 162,
        "X": -700.0,
        "Y": -600.0
    },
    {
        "id": 163,
        "X": -700.0,
        "Y": -500.0
    },
    {
        "id": 164,
        "X": -700.0,
        "Y": -400.0
    },
    {
        "id": 165,
        "X": -700.0,
        "Y": -300.0
    },
    {
        "id": 166,
        "X": -700.0,
        "Y": -200.0
    },
    {
        "id": 167,
        "X": -700.0,
        "Y": -100.0
    },
    {
        "id": 168,
        "X": -700.0,
        "Y": 0.0
    },
    {
        "id": 169,
        "X": -800.0,
        "Y": 0.0
    },
    {
        "id": 170,
        "X": -800.0,
        "Y": -100.0
    },
    {
        "id": 171,
        "X": -800.0,
        "Y": -200.0
    },
    {
        "id": 172,
        "X": -800.0,
        "Y": -300.0
    },
    {
        "id": 173,
        "X": -800.0,
        "Y": -400.0
    },
    {
        "id": 174,
        "X": -800.0,
        "Y": -500.0
    },
    {
        "id": 175,
        "X": -800.0,
        "Y": -600.0
    },
    {
        "id": 176,
        "X": -800.0,
        "Y": -700.0
    },
    {
        "id": 177,
        "X": -800.0,
        "Y": -800.0
    },
    {
        "id": 178,
        "X": -800.0,
        "Y": -900.0
    },
    {
        "id": 179,
        "X": -800.0,
        "Y": -1000.0
    },
    {
        "id": 180,
        "X": -800.0,
        "Y": -1100.0
    },
    {
        "id": 181,
        "X": -800.0,
        "Y": -1200.0
    },
    {
        "id": 182,
        "X": -800.0,
        "Y": -1300.0
    },
    {
        "id": 183,
        "X": -800.0,
        "Y": -1400.0
    },
    {
        "id": 184,
        "X": -800.0,
        "Y": -1500.0
    },
    {
        "id": 185,
        "X": -800.0,
        "Y": -1600.0
    },
    {
        "id": 186,
        "X": -800.0,
        "Y": -1700.0
    },
    {
        "id": 187,
        "X": -800.0,
        "Y": -1800.0
    },
    {
        "id": 188,
        "X": -800.0,
        "Y": -1900.0
    },
    {
        "id": 189,
        "X": -800.0,
        "Y": -2000.0
    },
    {
        "id": 190,
        "X": -900.0,
        "Y": -2000.0
    },
    {
        "id": 191,
        "X": -900.0,
        "Y": -1900.0
    },
    {
        "id": 192,
        "X": -900.0,
        "Y": -1800.0
    },
    {
        "id": 193,
        "X": -900.0,
        "Y": -1700.0
    },
    {
        "id": 194,
        "X": -900.0,
        "Y": -1600.0
    },
    {
        "id": 195,
        "X": -900.0,
        "Y": -1500.0
    },
    {
        "id": 196,
        "X": -900.0,
        "Y": -1400.0
    },
    {
        "id": 197,
        "X": -900.0,
        "Y": -1300.0
    },
    {
        "id": 198,
        "X": -900.0,
        "Y": -1200.0
    },
    {
        "id": 199,
        "X": -900.0,
        "Y": -1100.0
    },
    {
        "id": 200,
        "X": -900.0,
        "Y": -1000.0
    },
    {
        "id": 201,
        "X": -900.0,
        "Y": -900.0
    },
    {
        "id": 202,
        "X": -900.0,
        "Y": -800.0
    },
    {
        "id": 203,
        "X": -900.0,
        "Y": -700.0
    },
    {
        "id": 204,
        "X": -900.0,
        "Y": -600.0
    },
    {
        "id": 205,
        "X": -900.0,
        "Y": -500.0
    },
    {
        "id": 206,
        "X": -900.0,
        "Y": -400.0
    },
    {
        "id": 207,
        "X": -900.0,
        "Y": -300.0
    },
    {
        "id": 208,
        "X": -900.0,
        "Y": -200.0
    },
    {
        "id": 209,
        "X": -900.0,
        "Y": -100.0
    },
    {
        "id": 210,
        "X": -900.0,
        "Y": 0.0
    }
]